helloWorld/__init__.py
helloWorld/hello.py
givesNextNumber-0.0.1.dist-info/METADATA
givesNextNumber-0.0.1.dist-info/WHEEL
givesNextNumber-0.0.1.dist-info/top_level.txt
givesNextNumber-0.0.1.dist-info/RECORD
