Metadata-Version: 2.1
Name: givesNextNumber
Version: 0.0.1
Summary: Returns the next number
Author: Akash
Author-email: <akash.de117@gmail.com>
Keywords: python,number
Classifier: Development Status :: 1 - Planning
Classifier: Intended Audience :: Developers
Classifier: Programming Language :: Python :: 3
Classifier: Operating System :: Unix
Classifier: Operating System :: MacOS :: MacOS X
Classifier: Operating System :: Microsoft :: Windows
